AdapAttnIC.py
CharCNN.py
Inpainting.py
PSPNet.py
PointNet.py
StackGAN.py
UNet.py
UNetPP.py
modelzoo_iitm.py
resnet.py
AdapAttnIC_zoo/model.py
CharCNN_zoo/model.py
Inpainting_zoo/loss.py
Inpainting_zoo/model.py
Inpainting_zoo/train.py
Inpainting_zoo/utilities.py
PSPNet_zoo/model.py
PSPNet_zoo/resnet.py
PSPNet_zoo/train.py
PointNet/PointNet.py
PointNet/model.py
PointNet_zoo/model.py
PointNet_zoo/train.py
StackGAN_zoo/model.py
StackGAN_zoo/train1.py
StackGAN_zoo/train2.py
UNet/model.py
UNetPP_zoo/model.py
UNetPP_zoo/train.py
UNet_zoo/model.py
UNet_zoo/train.py
modelzoo_iitm-0.0.29.dist-info/LICENSE.txt
modelzoo_iitm-0.0.29.dist-info/METADATA
modelzoo_iitm-0.0.29.dist-info/WHEEL
modelzoo_iitm-0.0.29.dist-info/top_level.txt
modelzoo_iitm-0.0.29.dist-info/RECORD
