Metadata-Version: 2.1
Name: modelzoo-iitm
Version: 0.0.29
Summary: Model Zoo by IIT Madras
Home-page: https://github.com/Vinayak-VG/ModelZoo_PyPi
Author: Vinayak-VG
Author-email: vinayakguptapokal@gmail.com
License: UNKNOWN
Platform: UNKNOWN
Classifier: Programming Language :: Python :: 3
Classifier: Programming Language :: Python :: 3.6
Classifier: Programming Language :: Python :: 3.7
Classifier: License :: OSI Approved :: MIT License
Classifier: Operating System :: OS Independent
Requires-Dist: elasticdeform (~=0.4.9)
Requires-Dist: sentence-transformers (~=2.0.0)
Requires-Dist: PyPrind (~=2.11.3)
Provides-Extra: dev
Requires-Dist: pytest (>=3.7) ; extra == 'dev'
